grand_challenge_dicom_de_id_procedure/__init__.py
grand_challenge_dicom_de_id_procedure/procedure.json
grand_challenge_dicom_de_id_procedure-2025.10.1.dist-info/licenses/LICENSE.md
grand_challenge_dicom_de_id_procedure-2025.10.1.dist-info/METADATA
grand_challenge_dicom_de_id_procedure-2025.10.1.dist-info/WHEEL
grand_challenge_dicom_de_id_procedure-2025.10.1.dist-info/top_level.txt
grand_challenge_dicom_de_id_procedure-2025.10.1.dist-info/RECORD
