Metadata-Version: 2.4
Name: grand-challenge-dicom-de-id-procedure
Version: 2025.10.1
Summary: De-identification procedure that descibes how to de-identify DICOM files
License:                                  Apache License
License-File: LICENSE.md
Dynamic: license-file
